academic_refchecker-2.0.20.dist-info/licenses/LICENSE
backend/__init__.py
backend/__main__.py
backend/cli.py
backend/concurrency.py
backend/database.py
backend/main.py
backend/models.py
backend/refchecker_wrapper.py
backend/thumbnail.py
backend/websocket_manager.py
backend/static/favicon.svg
backend/static/index.html
backend/static/vite.svg
backend/static/assets/index-2P6L_39v.css
backend/static/assets/index-B92lKsA8.js
backend/static/assets/index-BuguAhjS.css
backend/static/assets/index-DMZJNrR0.js
backend/static/assets/index-hk21nqxR.js
refchecker/__init__.py
refchecker/__main__.py
refchecker/__version__.py
refchecker/checkers/__init__.py
refchecker/checkers/arxiv_citation.py
refchecker/checkers/crossref.py
refchecker/checkers/enhanced_hybrid_checker.py
refchecker/checkers/github_checker.py
refchecker/checkers/local_semantic_scholar.py
refchecker/checkers/openalex.py
refchecker/checkers/openreview_checker.py
refchecker/checkers/pdf_paper_checker.py
refchecker/checkers/semantic_scholar.py
refchecker/checkers/webpage_checker.py
refchecker/config/__init__.py
refchecker/config/logging.conf
refchecker/config/settings.py
refchecker/core/__init__.py
refchecker/core/db_connection_pool.py
refchecker/core/parallel_processor.py
refchecker/core/refchecker.py
refchecker/database/__init__.py
refchecker/database/download_semantic_scholar_db.py
refchecker/llm/__init__.py
refchecker/llm/base.py
refchecker/llm/providers.py
refchecker/scripts/__init__.py
refchecker/scripts/start_vllm_server.py
refchecker/services/__init__.py
refchecker/services/pdf_processor.py
refchecker/utils/__init__.py
refchecker/utils/arxiv_rate_limiter.py
refchecker/utils/arxiv_utils.py
refchecker/utils/author_utils.py
refchecker/utils/biblatex_parser.py
refchecker/utils/bibliography_utils.py
refchecker/utils/bibtex_parser.py
refchecker/utils/config_validator.py
refchecker/utils/db_utils.py
refchecker/utils/doi_utils.py
refchecker/utils/error_utils.py
refchecker/utils/mock_objects.py
refchecker/utils/text_utils.py
refchecker/utils/unicode_utils.py
academic_refchecker-2.0.20.dist-info/METADATA
academic_refchecker-2.0.20.dist-info/WHEEL
academic_refchecker-2.0.20.dist-info/entry_points.txt
academic_refchecker-2.0.20.dist-info/top_level.txt
academic_refchecker-2.0.20.dist-info/RECORD
