Metadata-Version: 2.4
Name: academic-refchecker
Version: 2.0.20
Summary: A comprehensive tool for validating reference accuracy in academic papers
Author-email: Mark Russinovich <markrussinovich@hotmail.com>
License-Expression: MIT
Project-URL: Homepage, https://github.com/markrussinovich/refchecker
Project-URL: Repository, https://github.com/markrussinovich/refchecker
Project-URL: Bug Tracker, https://github.com/markrussinovich/refchecker/issues
Classifier: Development Status :: 4 - Beta
Classifier: Intended Audience :: Science/Research
Classifier: Topic :: Scientific/Engineering :: Information Analysis
Classifier: Programming Language :: Python :: 3
Classifier: Programming Language :: Python :: 3.7
Classifier: Programming Language :: Python :: 3.8
Classifier: Programming Language :: Python :: 3.9
Classifier: Programming Language :: Python :: 3.10
Classifier: Programming Language :: Python :: 3.11
Classifier: Operating System :: OS Independent
Requires-Python: >=3.7
License-File: LICENSE
Requires-Dist: requests>=2.25.0
Requires-Dist: beautifulsoup4>=4.9.0
Requires-Dist: pypdf>=5.0.0
Requires-Dist: arxiv>=1.4.0
Requires-Dist: python-dateutil>=2.8.0
Requires-Dist: tqdm>=4.60.0
Requires-Dist: colorama>=0.4.4
Requires-Dist: fuzzywuzzy>=0.18.0
Requires-Dist: python-Levenshtein>=0.12.0
Requires-Dist: pandas<2.4.0,>=1.3.0
Requires-Dist: numpy<2.0.0,>=1.22.4
Requires-Dist: pdfplumber>=0.6.0
Requires-Dist: bibtexparser>=1.4.0
Provides-Extra: dev
Requires-Dist: pytest>=6.0.0; extra == "dev"
Requires-Dist: pytest-cov>=2.0.0; extra == "dev"
Requires-Dist: black>=21.0.0; extra == "dev"
Requires-Dist: isort>=5.0.0; extra == "dev"
Requires-Dist: flake8>=3.9.0; extra == "dev"
Requires-Dist: mypy>=0.910; extra == "dev"
Provides-Extra: docs
Requires-Dist: sphinx>=4.0.0; extra == "docs"
Requires-Dist: sphinx-rtd-theme>=0.5.0; extra == "docs"
Provides-Extra: llm
Requires-Dist: openai>=1.0.0; extra == "llm"
Requires-Dist: anthropic>=0.7.0; extra == "llm"
Requires-Dist: google-generativeai>=0.3.0; extra == "llm"
Provides-Extra: optional
Requires-Dist: lxml>=4.6.0; extra == "optional"
Requires-Dist: selenium>=4.0.0; extra == "optional"
Requires-Dist: pikepdf>=5.0.0; extra == "optional"
Requires-Dist: nltk>=3.6.0; extra == "optional"
Requires-Dist: scikit-learn>=1.0.0; extra == "optional"
Requires-Dist: joblib>=1.1.0; extra == "optional"
Provides-Extra: vllm
Requires-Dist: vllm>=0.3.0; extra == "vllm"
Requires-Dist: huggingface_hub>=0.17.0; extra == "vllm"
Requires-Dist: torch>=2.0.0; extra == "vllm"
Provides-Extra: webui
Requires-Dist: fastapi>=0.100.0; extra == "webui"
Requires-Dist: uvicorn[standard]>=0.22.0; extra == "webui"
Requires-Dist: pydantic>=2.0.0; extra == "webui"
Requires-Dist: aiosqlite>=0.19.0; extra == "webui"
Requires-Dist: httpx>=0.24.0; extra == "webui"
Requires-Dist: cryptography>=42.0.0; extra == "webui"
Requires-Dist: pymupdf>=1.23.0; extra == "webui"
Requires-Dist: Pillow>=9.0.0; extra == "webui"
Requires-Dist: python-multipart>=0.0.6; extra == "webui"
Dynamic: license-file
